[{
    "companyName": "Nlounge",
    "companyLogo": "Violet",
    "email": "tdorgon0@123-reg.co.uk",
    "address": "6636 Duke Plaza",
    "description": "Reposition Left Lower Femur with Int Fix, Perc Endo Approach"
  }, {
    "companyName": "Skaboo",
    "companyLogo": "Puce",
    "email": "darundel1@flavors.me",
    "address": "22 Esker Place",
    "description": "Destruction of Rectum, Percutaneous Approach"
  }, {
    "companyName": "Meetz",
    "companyLogo": "Maroon",
    "email": "koffer2@upenn.edu",
    "address": "8 Fairfield Drive",
    "description": "Excision of Chordae Tendineae, Open Approach"
  }, {
    "companyName": "Skibox",
    "companyLogo": "Purple",
    "email": "kdri3@nyu.edu",
    "address": "15455 Sunbrook Lane",
    "description": "Replace R Lacrimal Bone w Nonaut Sub, Perc Endo"
  }, {
    "companyName": "Flashspan",
    "companyLogo": "Yellow",
    "email": "jbrownfield4@lycos.com",
    "address": "04515 Scott Avenue",
    "description": "Excision of R Metacarpophal Jt, Perc Endo Approach, Diagn"
  }]